extools/__init__.py
extools/errors.py
extools/expi.json
extools/exmessages/__init__.py
extools/extest/__init__.py
extools/extest/vi/extools.testrunner.vi
extools/exui/__init__.py
extools/exui/bare.py
extools/exview/__init__.py
extools/exview/errors.py
extools/exview/exsql.py
extools/tests/__init__.py
extools/tests/extest_extools.py
extools/tests/test_extools.py
extools/vi/extools.testrunner.vi
extools-0.3.0.dist-info/LICENSE.txt
extools-0.3.0.dist-info/METADATA
extools-0.3.0.dist-info/WHEEL
extools-0.3.0.dist-info/top_level.txt
extools-0.3.0.dist-info/RECORD
